pdkslibrary/__init__.py
pdkslibrary/betamods.py
pdkslibrary-2.0.2.dist-info/METADATA
pdkslibrary-2.0.2.dist-info/WHEEL
pdkslibrary-2.0.2.dist-info/top_level.txt
pdkslibrary-2.0.2.dist-info/RECORD
