Metadata-Version: 2.1
Name: pdkslibrary
Version: 2.0.2
Summary: For PDKS platform engineering purposes
Home-page: UNKNOWN
Author: Michael Shobitan
Author-email: UNKNOWN
License: PDKS
Platform: UNKNOWN
